requests_proxy_adapter/__init__.py
requests_proxy_adapter/api.py
requests_proxy_adapter/exceptions.py
requests_proxy_adapter/version.py
requests_proxy_adapter-0.1.1.dist-info/METADATA
requests_proxy_adapter-0.1.1.dist-info/RECORD
requests_proxy_adapter-0.1.1.dist-info/WHEEL
requests_proxy_adapter-0.1.1.dist-info/pbr.json
requests_proxy_adapter-0.1.1.dist-info/top_level.txt
