Metadata-Version: 2.1
Name: requests-proxy-adapter
Version: 0.1.1
Summary: Set of Proxy Transport Adapters fro Requests
Home-page: https://github.com/otetz/requests_proxy_adapter
Author: Alexey Shevchenko
Author-email: otetz@me.com
License: MIT license
Keywords: requests,proxy
Platform: UNKNOWN
Classifier: Development Status :: 2 - Pre-Alpha
Classifier: Intended Audience :: Developers
Classifier: Intended Audience :: Information Technology
Classifier: License :: OSI Approved :: MIT License
Classifier: Natural Language :: English
Classifier: Programming Language :: Python
Classifier: Programming Language :: Python :: 2
Classifier: Programming Language :: Python :: 2.7
Classifier: Programming Language :: Python :: 3
Classifier: Programming Language :: Python :: 3.5
Classifier: Programming Language :: Python :: 3.6
Classifier: Programming Language :: Python :: 3.7
Requires-Dist: pluggy (==0.11.0)
Requires-Dist: requests (==2.22.0)
Requires-Dist: urllib3 (>=1.15)
Provides-Extra: dev
Requires-Dist: flake8 (==3.7.7); extra == 'dev'
Requires-Dist: Sphinx (==2.0.1); extra == 'dev'
Provides-Extra: test
Requires-Dist: tox (==3.11.1); extra == 'test'
Requires-Dist: coverage (==4.5.3); extra == 'test'
Requires-Dist: pytest (==4.5.0); extra == 'test'
Requires-Dist: pytest-runner (==4.4); extra == 'test'
Requires-Dist: pytest-cov (==2.7.1); extra == 'test'
Requires-Dist: flaky (==3.5.3); extra == 'test'
